matrix.py
matrix_path-1.1.1.dist-info/LICENSE
matrix_path-1.1.1.dist-info/METADATA
matrix_path-1.1.1.dist-info/WHEEL
matrix_path-1.1.1.dist-info/top_level.txt
matrix_path-1.1.1.dist-info/RECORD
