Metadata-Version: 2.1
Name: matrix-path
Version: 1.1.1
Summary: Navigating and Visualizing paths in a 2D Matrix.
Home-page: https://github.com/rushmash91/matrix_path
Author: Arush Sharma
Author-email: arushsharma91@gmail.com
License: MIT
Platform: UNKNOWN
Classifier: License :: OSI Approved :: MIT License
Classifier: Programming Language :: Python :: 3.6
Classifier: Programming Language :: Python :: 3.7
Classifier: Programming Language :: Python :: 3.8
